{
  "incumbent_ids": [
    142
  ],
  "rejected_config_ids": [
    2,
    1,
    4,
    6,
    7,
    8,
    9,
    10,
    11,
    5,
    14,
    15,
    13,
    16,
    12,
    18,
    17,
    19,
    23,
    22,
    20,
    24,
    25,
    26,
    21,
    27,
    30,
    31,
    29,
    32,
    34,
    33,
    28,
    35,
    38,
    39,
    36,
    40,
    41,
    37,
    42,
    43,
    44,
    46,
    45,
    47,
    48,
    49,
    50,
    51,
    54,
    55,
    52,
    56,
    57,
    58,
    3,
    53,
    59,
    60,
    65,
    63,
    62,
    64,
    66,
    67,
    68,
    69,
    70,
    71,
    61,
    74,
    73,
    76,
    77,
    78,
    79,
    81,
    75,
    72,
    82,
    83,
    84,
    85,
    86,
    87,
    88,
    90,
    80,
    91,
    92,
    94,
    95,
    96,
    102,
    103,
    101,
    100,
    104,
    105,
    107,
    106,
    109,
    111,
    108,
    110,
    112,
    113,
    114,
    115,
    116,
    118,
    119,
    89,
    120,
    121,
    123,
    122,
    124,
    125,
    126,
    127,
    128,
    129,
    131,
    132,
    130,
    133,
    134,
    136,
    135,
    137,
    138,
    139,
    140,
    141,
    117,
    143,
    144,
    145,
    146,
    147,
    148,
    149,
    150
  ],
  "incumbents_changed": 10,
  "trajectory": [
    {
      "config_ids": [
        2
      ],
      "costs": [
        0.5067333183292051
      ],
      "trial": 1,
      "walltime": 457.9729390144348
    },
    {
      "config_ids": [
        3
      ],
      "costs": [
        0.431903381753461
      ],
      "trial": 2,
      "walltime": 468.6452085971832
    },
    {
      "config_ids": [
        60
      ],
      "costs": [
        0.4153824978390782
      ],
      "trial": 58,
      "walltime": 9588.017453432083
    },
    {
      "config_ids": [
        61
      ],
      "costs": [
        0.40274887244233515
      ],
      "trial": 61,
      "walltime": 9660.999711990356
    },
    {
      "config_ids": [
        73
      ],
      "costs": [
        0.39178119582855486
      ],
      "trial": 72,
      "walltime": 11341.274402856827
    },
    {
      "config_ids": [
        75
      ],
      "costs": [
        0.36693045883381936
      ],
      "trial": 74,
      "walltime": 11532.072971343994
    },
    {
      "config_ids": [
        80
      ],
      "costs": [
        0.36401498980026814
      ],
      "trial": 80,
      "walltime": 12413.01711153984
    },
    {
      "config_ids": [
        89
      ],
      "costs": [
        0.3297237500653868
      ],
      "trial": 90,
      "walltime": 13562.218985557556
    },
    {
      "config_ids": [
        117
      ],
      "costs": [
        0.32500349875996226
      ],
      "trial": 115,
      "walltime": 16921.58898997307
    },
    {
      "config_ids": [
        142
      ],
      "costs": [
        0.3145911405417682
      ],
      "trial": 138,
      "walltime": 20322.770416021347
    }
  ],
  "state": {
    "queue": [
      [
        99,
        1
      ],
      [
        150,
        1
      ]
    ]
  }
}